<?xml version="1.0" encoding="UTF-8"?>
<SOAP-ENV:Envelope xmlns:SOAP-ENV="http://schemas.xmlsoap.org/soap/envelope/" xmlns:of="http://oss.dbc.dk/ns/openformat" xmlns:ofo="http://oss.dbc.dk/ns/openformatoutput"><SOAP-ENV:Body><of:formatResponse><ofo:fullDisplayHtml><ofo:manifestation><ofo:main><ofo:title>&lt;div class="title"&gt;Evolve&lt;/div&gt;</ofo:title><ofo:type>&lt;div class="types"&gt;&lt;span class="type"&gt;Playstation 4&lt;/span&gt;&lt;/div&gt;</ofo:type><ofo:description>&lt;div class="abstract"&gt;&lt;span class="abstractElement"&gt;Shooter. På den fremmede planet Shear kæmper mennesker, i grupper af fire, mod planetens oprindelige beboere: store kødædende monstre&lt;/span&gt;&lt;/div&gt;</ofo:description><ofo:details>&lt;div class="abstract"&gt;&lt;span class="abstractElement"&gt;Shooter. På den fremmede planet Shear kæmper mennesker, i grupper af fire, mod planetens oprindelige beboere: store kødædende monstre&lt;/span&gt;&lt;/div&gt;&lt;div class="contributors"&gt;developed by Turtle Rock Studios&lt;/div&gt;&lt;div class="format"&gt;1 blu-ray disc (blu-ray) (playstation 4) + 1 vejledning&lt;/div&gt;&lt;div class="forms"&gt;&lt;span class="formHeader"&gt;Form: &lt;/span&gt;&lt;span class="formSubject phraseLink"&gt;computerspil&lt;/span&gt; ; &lt;span class="formSubject phraseLink"&gt;shooters&lt;/span&gt;&lt;/div&gt;&lt;div class="shelf"&gt;&lt;span class="shelfHeader"&gt;Opstilling i folkebiblioteker: &lt;/span&gt;&lt;span class="classification phraseLink"&gt;79.41&lt;/span&gt;&lt;/div&gt;&lt;div class="genre"&gt;Spil for 1 spiller&lt;/div&gt;&lt;div class="audiencePegi"&gt;&lt;span class="audiencePegiHeader"&gt;Europæisk PEGI-mærkning: &lt;/span&gt;&lt;span class="audiencePegiElement"&gt;16&lt;/span&gt;&lt;/div&gt;&lt;div class="systemDemands"&gt;&lt;span class="systemDemandsDescriptor"&gt;Afspilningsudstyr: &lt;/span&gt;&lt;span class="systemDemandsElement"&gt;Sony playstation 4; understøtter vibrationsfunktion; understøtter Playstation Vita. - Med multiplayerfunktion&lt;/span&gt;&lt;/div&gt;</ofo:details><ofo:publicationDetails>&lt;span class="publisher"&gt;Take-Two Interactive Software&lt;/span&gt;, &lt;span class="year"&gt;2015&lt;/span&gt;</ofo:publicationDetails></ofo:main></ofo:manifestation></ofo:fullDisplayHtml></of:formatResponse></SOAP-ENV:Body></SOAP-ENV:Envelope>
